fastapi_event_emitter/__init__.py
fastapi_event_emitter/decorators/event.py
fastapi_event_emitter/decorators/observer.py
fastapi_event_emitter/dependencies/event_emitter.py
fastapi_event_emitter/helpers/dependency.py
fastapi_event_emitter/services/event_emitter.py
fastapi_event_emitter/services/event_handler.py
fastapi_event_emitter-0.0.2.dist-info/METADATA
fastapi_event_emitter-0.0.2.dist-info/WHEEL
fastapi_event_emitter-0.0.2.dist-info/licenses/LICENSE
fastapi_event_emitter-0.0.2.dist-info/RECORD
