Metadata-Version: 2.1
Name: fastapi_event_emitter
Version: 0.0.2
Summary: FastAPI Event
Project-URL: Homepage, https://github.com/megatron-global/fastapi-event
Project-URL: Bug Tracker, https://github.com/megatron-global/fastapi-event/issues
Author-email: Dzung Nguyen <dung@megatron-solutions.com>
License-File: LICENSE
Classifier: License :: OSI Approved :: MIT License
Classifier: Operating System :: OS Independent
Classifier: Programming Language :: Python :: 3
Requires-Python: >=3.10
